{
  "name": "Root",
  "fields": [
    {
      "offset": "0x00_00_00_00",
      "description": "Current",
      "type": "container:Current"
    },
    {
      "offset": "0x01_00_00_00",
      "description": "Setup",
      "type": "container:Setup"
    },
    {
      "offset": "0x02_00_00_00",
      "description": "Trigger",
      "type": "container:Trigger"
    },
    {
      "offset": "0x03_00_00_00",
      "description": "Set List",
      "type": "container:SetListParams",
      "repeat": "$setLists",
      "gap": "0x10_00"
    },
    {
      "offset": "0x04_00_00_00",
      "description": "Kit",
      "type": "container:Kit",
      "repeat": "$kits",
      "gap": "0x02_00_00"
    }
  ]
}
